Metadata-Version: 2.1
Name: vireoSNP
Version: 0.5.9
Summary: vireoSNP - donor deconvolution for multiplexed scRNA-seq data
Home-page: https://github.com/huangyh09/vireoSNP
Author: Yuanhua Huang
Author-email: yuanhua@ebi.ac.uk
License: Apache-2.0
Keywords: allelic expression,multiplexed single-cell RNA-seq,variantional inference
License-File: LICENSE
Requires-Dist: numpy>=1.9.0
Requires-Dist: scipy>=1.4.0
Requires-Dist: matplotlib
Provides-Extra: docs
Requires-Dist: sphinx_bootstrap_theme; extra == "docs"
